[
  {
    "id": "b7e7dc4d-4e2c-49ff-8edb-2103c8f92ece",
    "kind": "item",
    "description": "Can get any Build from 2.5 to 15$!",
    "owner": "us-east-1:630b10b1-32f8-419c-b6e5-aceafb3502a3",
    "category": "DIGITAL_INGAME",
    "name": "Bundle | Stw Mystery Build Fortni",
    "platform": "unknown",
    "price": 500,
    "accept_currency": "USD",
    "upc": "GFFORTNITE",
    "cognitoidp_client": "marketplace",
    "tags": [
      "id: bundle",
      "type: Custom"
    ],
    "digital": true,
    "digital_region": "none",
    "digital_deliverable": "transfer",
    "photo": {
      "571df04f-5ad5-4ff3-9e90-b6ebcc71f4d7": {
        "display_order": 0,
        "status": "active",
        "view_url": "https://production-gameflipusercontent.fingershock.com/us-east-1:630b10b1-32f8-419c-b6e5-aceafb3502a3/b7e7dc4d-4e2c-49ff-8edb-2103c8f92ece/571df04f-5ad5-4ff3-9e90-b6ebcc71f4d7"
      }
    },
    "status": "onsale",
    "shipping_predefined_package": "None",
    "shipping_fee": 0,
    "shipping_paid_by": "seller",
    "shipping_within_days": 3,
    "expire_in_days": 7,
    "expiration": "2025-02-23T20:00:28.298Z",
    "visibility": "public",
    "seller_id_verified": "2024-12-08T12:56:45.357Z",
    "seller_score": 0.9904873594003194,
    "seller_ratings": 1349,
    "created": "2025-02-16T20:00:28.298Z",
    "updated": "2025-02-16T20:00:30.246Z",
    "version": "2",
    "image_urls": [
      "gameflip_data_20250216_210135\\images\\b7e7dc4d-4e2c-49ff-8edb-2103c8f92ece_571df04f-5ad5-4ff3-9e90-b6ebcc71f4d7.jpg"
    ]
  },
  {
    "id": "c7c7cf7d-60e6-438d-8b4b-c3ff7fbc2dfe",
    "kind": "item",
    "description": "Huge Stunt Cat Corgi Fireball Cat",
    "owner": "us-east-1:fff430f2-ccc7-4dd5-b520-494437a25b2f",
    "category": "DIGITAL_INGAME",
    "name": "Huge Stunt Cat Corgi Fireball Cat",
    "price": 499,
    "accept_currency": "USD",
    "upc": "GF0000ROBLOX",
    "cognitoidp_client": "marketplace",
    "tags": [
      "type: Pet",
      "roblox_game: Pet Simulator 99"
    ],
    "digital": true,
    "digital_deliverable": "transfer",
    "photo": {
      "bc5c3ee8-9ec4-418b-9bac-0b7ceb50b3cb": {
        "display_order": 0,
        "status": "active",
        "view_url": "https://production-gameflipusercontent.fingershock.com/us-east-1:fff430f2-ccc7-4dd5-b520-494437a25b2f/c7c7cf7d-60e6-438d-8b4b-c3ff7fbc2dfe/bc5c3ee8-9ec4-418b-9bac-0b7ceb50b3cb"
      }
    },
    "status": "onsale",
    "shipping_fee": 0,
    "shipping_paid_by": "seller",
    "shipping_within_days": 1,
    "expire_in_days": 7,
    "expiration": "2025-02-23T20:00:44.394Z",
    "visibility": "public",
    "seller_id_verified": "2024-06-11T18:14:59.826Z",
    "seller_score": 0.9946108644613334,
    "seller_ratings": 1595,
    "seller_online_until": "2025-02-16T21:57:58.916Z",
    "created": "2025-02-16T20:00:41.339Z",
    "updated": "2025-02-16T20:00:44.394Z",
    "version": "3",
    "image_urls": [
      "gameflip_data_20250216_210135\\images\\c7c7cf7d-60e6-438d-8b4b-c3ff7fbc2dfe_bc5c3ee8-9ec4-418b-9bac-0b7ceb50b3cb.jpg"
    ]
  }
]